facialmatch/__init__.py
facialmatch/main.py
facialmatch-1.0.1.dist-info/LICENSE
facialmatch-1.0.1.dist-info/METADATA
facialmatch-1.0.1.dist-info/WHEEL
facialmatch-1.0.1.dist-info/top_level.txt
facialmatch-1.0.1.dist-info/RECORD
