Metadata-Version: 2.1
Name: facialmatch
Version: 1.0.1
Summary: face matching
Author: Hemang Baldha
Author-email: hemang9705@gmail.com
Keywords: python,face,face matching,face detection,face recognition,opencv,opencv-python,numpy,scikit-learn
License-File: LICENSE
Requires-Dist: opencv-python
Requires-Dist: numpy
Requires-Dist: scikit-learn
